lib/__init__.py
lib/mnemonic.py
wigfrid/__init__.py
wigfrid/bip32.py
wigfrid/bip39.py
wigfrid/mnemonic.py
wigfrid-0.1.4.dist-info/METADATA
wigfrid-0.1.4.dist-info/WHEEL
wigfrid-0.1.4.dist-info/top_level.txt
wigfrid-0.1.4.dist-info/RECORD
