Metadata-Version: 2.1
Name: wigfrid
Version: 0.1.4
Summary: My Python library of building filecoin apps
Home-page: UNKNOWN
Author: Faucre
Author-email: UNKNOWN
License: MIT
Platform: UNKNOWN
Requires-Dist: cbor2 (==5.2.0)
Requires-Dist: ecdsa (==0.16.1)
Requires-Dist: mnemonic (==0.19)
Requires-Dist: pbkdf2 (==1.3)
